labelsnow/__init__.py
labelsnow/add_json_answers_to_dictionary.py
labelsnow/constants.py
labelsnow/create_dataset.py
labelsnow/flatten_bronze_table.py
labelsnow/get_annotations.py
labelsnow/get_snowflake_datarows.py
labelsnow/get_videoframe_annotations.py
labelsnow/is_json.py
labelsnow/put_tables_into_snowflake.py
labelsnow/silver_table.py
labelsnow-1.1.0.dist-info/LICENSE
labelsnow-1.1.0.dist-info/METADATA
labelsnow-1.1.0.dist-info/WHEEL
labelsnow-1.1.0.dist-info/top_level.txt
labelsnow-1.1.0.dist-info/RECORD
