Metadata-Version: 2.1
Name: labelsnow
Version: 1.1.0
Summary: Labelbox Connector for Snowflake
Home-page: https://labelbox.com
Author: Labelbox
Author-email: ecosystem+snowflake@labelbox.com
Keywords: labelbox,labelsnow
License-File: LICENSE
Requires-Dist: labelbox
Requires-Dist: pandas >=2.1.0
Requires-Dist: snowflake-connector-python
